{"nodes": [{"id": "doc.deploy.startup", "label": "10-startup-order.md", "type": "file", "summary": "Start/stop ordering for all components, with health-check one-liner", "source_file": "docs/deploy/10-startup-order.md", "source_location": "/Users/earlpan3/projects/i/phone-analysis/docs/deploy/10-startup-order.md:L1-L107", "confidence": "EXTRACTED"}, {"id": "component.redis", "label": "Redis 6.2.7", "type": "module", "summary": "Redis cache for Spring Boot app", "source_file": "docs/deploy/10-startup-order.md", "source_location": "/Users/earlpan3/projects/i/phone-analysis/docs/deploy/10-startup-order.md:L8", "confidence": "EXTRACTED"}], "edges": [], "hyperedges": []}